ec2stepshell/__init__.py
ec2stepshell/__main__.py
ec2stepshell/core/ReverseShell.py
ec2stepshell/ssm/SsmWrapper.py
ec2stepshell/utils/ArgumentsHandler.py
ec2stepshell/utils/CommandOutput.py
ec2stepshell/utils/constants.py
ec2stepshell/utils/terminal/TerminalEmulator.py
EC2StepShell-1.1.2.dist-info/LICENCE.txt
EC2StepShell-1.1.2.dist-info/METADATA
EC2StepShell-1.1.2.dist-info/WHEEL
EC2StepShell-1.1.2.dist-info/entry_points.txt
EC2StepShell-1.1.2.dist-info/top_level.txt
EC2StepShell-1.1.2.dist-info/RECORD
