Metadata-Version: 2.1
Name: EC2StepShell
Version: 1.1.2
Summary: EC2StepShell is an AWS post-exploitation tool for getting reverse shells in public or private EC2 instances
Author-email: Eduard Agavriloae <eduard.agavriloae@hacktodef.com>
License: Copyright 2023 saw-your-packet
Project-URL: Homepage, https://github.com/saw-your-packet/EC2StepShell
Keywords: cloud security,AWS,EC2StepShell
Classifier: Development Status :: 5 - Production/Stable
Classifier: Intended Audience :: Information Technology
Classifier: License :: OSI Approved :: MIT License
Classifier: Operating System :: OS Independent
Classifier: Programming Language :: Python :: 3
Classifier: Topic :: Security
Requires-Python: >=3.6
License-File: LICENCE.txt
Requires-Dist: colorama
Requires-Dist: termcolor
Requires-Dist: pyfiglet
Requires-Dist: boto3
